JAEN/__init__.py
JAEN/competition.py
JAEN/datasets.py
JAEN/jaen.py
JAEN/models.py
JAEN/utils.py
JAEN/data/models.pth
JAEN/data/00/test_loader.pt
JAEN/data/00/train_loader.pt
JAEN/data/01/X_test_tensor.pt
JAEN/data/01/X_train_tensor.pt
JAEN/data/01/sale_price_tensor.pt
JAEN/data/01/y_train_tensor.pt
JAEN/data/02/x_test.pt
JAEN/data/02/x_train.pt
JAEN/data/02/y_test.pt
JAEN/data/02/y_train.pt
JAEN/data/03/x_test.pt
JAEN/data/03/x_train.pt
JAEN/data/03/y_test.pt
JAEN/data/03/y_train.pt
JAEN/data/certi/abalone.csv
JAEN/data/certi/air_quality.csv
JAEN/data/certi/automobile.csv
JAEN/data/certi/bank_marketing.csv
JAEN/data/certi/boston.csv
JAEN/data/certi/breast_cancer.csv
JAEN/data/certi/car_evaluation.csv
JAEN/data/certi/credit_approval.csv
JAEN/data/certi/dry_bean.csv
JAEN/data/certi/forest_fires.csv
JAEN/data/certi/heart_disease.csv
JAEN/data/certi/iris_dataset.csv
JAEN/data/certi/mushroom.csv
JAEN/data/certi/real_estate_valuation.csv
JAEN/data/certi/wine.csv
jaen-1.1.5.dist-info/METADATA
jaen-1.1.5.dist-info/WHEEL
jaen-1.1.5.dist-info/top_level.txt
jaen-1.1.5.dist-info/RECORD
