Metadata-Version: 2.4
Name: JAEN
Version: 1.1.5
Summary: 차별화된 자체 교육 콘텐츠와 실무 중심 교육
Home-page: https://github.com/BAEM1N/JAEN
Author: BAEM1N
Author-email: baemin.dev@gmail.com
Keywords: AI,ML,DL
Classifier: Programming Language :: Python :: 3
Requires-Python: >=3
Requires-Dist: pandas
Requires-Dist: ragas
Requires-Dist: boston
Requires-Dist: scikit-learn
Requires-Dist: torchinfo
Dynamic: author
Dynamic: author-email
Dynamic: classifier
Dynamic: home-page
Dynamic: keywords
Dynamic: requires-dist
Dynamic: requires-python
Dynamic: summary
